happy_quotas/__init__.py
happy_quotas/admin.py
happy_quotas/apps.py
happy_quotas/migrations/0001_initial.py
happy_quotas/migrations/__init__.py
happy_quotas/models.py
happy_quotas/tests.py
dj_happy_quotas-0.1.0.dist-info/LICENSE
dj_happy_quotas-0.1.0.dist-info/WHEEL
dj_happy_quotas-0.1.0.dist-info/METADATA
dj_happy_quotas-0.1.0.dist-info/RECORD
