Metadata-Version: 2.1
Name: dj-happy-quotas
Version: 0.1.0
Summary: Transaction-based quotas for Django
Home-page: https://codeberg.org/buechergefahr/dj-happy-quotas
Keywords: quotas,credits,saas
Author: Señor Rolando
Author-email: rolando@buechergefahr.de
Maintainer: Señor Rolando
Maintainer-email: rolando@buechergefahr.de
Requires-Python: >=3.7,<4.0
Classifier: Development Status :: 4 - Beta
Classifier: Environment :: Web Environment
Classifier: Framework :: Django :: 3.0
Classifier: Intended Audience :: Developers
Classifier: License :: OSI Approved :: BSD License
Classifier: Programming Language :: Python :: 3
Classifier: Programming Language :: Python :: 3.7
Classifier: Programming Language :: Python :: 3.8
Project-URL: Bug Tracker, https://codeberg.org/buechergefahr/dj-happy-quotas/issues
Project-URL: Repository, https://codeberg.org/buechergefahr/dj-happy-quotas
